{
  "sim_id": "88a739b4",
  "moa_category": "TGFBR1 inhibitor",
  "total_drugs": 2,
  "total_trials": 3,
  "median_response_rate": 0.0,
  "overall_learned_threshold": 0.9979625,
  "threshold_std": 0.020715449397732115,
  "total_training_thresholds": 1000,
  "moa_drug_names": [
    "GALUNISERTIB",
    "LY2157299"
  ],
  "training_trials": [
    {
      "nct_id": "NCT01582269:Arm A: Galunisertib",
      "title": "A Study in Recurrent Glioblastoma (GB)",
      "arm_group": "Arm A: Galunisertib",
      "enrollment": 39,
      "actual_response_rate": 0.0,
      "drugs": [
        "GALUNISERTIB"
      ],
      "all_trial_drugs": [
        "LOMUSTINE",
        "GALUNISERTIB"
      ],
      "arm_drugs": [
        "GALUNISERTIB"
      ],
      "molecular_criteria": [
        "Recurrent",
        "Prior Bevacizumab"
      ],
      "eligible_patients": 217,
      "total_patients": 548,
      "cohort_size": 39,
      "mean_threshold": 0.9979625,
      "std_threshold": 0.020715449397732115,
      "mean_predicted_rate": 0.0
    }
  ],
  "testing_trials": [
    {
      "nct_id": "NCT01582269:Arm C: Lomustine + Placebo",
      "title": "A Study in Recurrent Glioblastoma (GB)",
      "arm_group": "Arm C: Lomustine + Placebo",
      "enrollment": 40,
      "actual_response_rate": 0.0,
      "drugs": [
        "LOMUSTINE",
        "GALUNISERTIB"
      ],
      "all_trial_drugs": [
        "LOMUSTINE",
        "GALUNISERTIB"
      ],
      "arm_drugs": [
        "LOMUSTINE",
        "GALUNISERTIB"
      ],
      "molecular_criteria": [
        "Recurrent",
        "Prior Bevacizumab"
      ],
      "eligible_patients": 217,
      "total_patients": 548,
      "cohort_size": 40,
      "mean_predicted_rate": 0.004775000000000001,
      "std_predicted_rate": 0.009827226210889826
    },
    {
      "nct_id": "NCT01582269:Arm B: Galunisertib + Lomustine",
      "title": "A Study in Recurrent Glioblastoma (GB)",
      "arm_group": "Arm B: Galunisertib + Lomustine",
      "enrollment": 79,
      "actual_response_rate": 0.013,
      "drugs": [
        "LOMUSTINE",
        "GALUNISERTIB"
      ],
      "all_trial_drugs": [
        "LOMUSTINE",
        "GALUNISERTIB"
      ],
      "arm_drugs": [
        "LOMUSTINE",
        "GALUNISERTIB"
      ],
      "molecular_criteria": [
        "Recurrent",
        "Prior Bevacizumab"
      ],
      "eligible_patients": 217,
      "total_patients": 548,
      "cohort_size": 79,
      "mean_predicted_rate": 0.004582278481012659,
      "std_predicted_rate": 0.006083276173128911
    }
  ],
  "testing_violin_data": [
    {
      "nct_id": "NCT01582269:Arm C: Lomustine + Placebo",
      "title": "A Study in Recurrent Glioblastoma (GB)",
      "drugs": [
        "LOMUSTINE",
        "GALUNISERTIB"
      ],
      "actual_response_rate": 0.0,
      "predicted_rates": [
        0.0,
        0.0,
        0.0,
        0.0,
        0.025,
        0.0,
        0.0,
        0.0,
        0.0,
        0.0,
        0.0,
        0.0,
        0.0,
        0.0,
        0.0,
        0.025,
        0.0,
        0.0,
        0.0,
        0.0,
        0.0,
        0.0,
        0.0,
        0.0,
        0.0,
        0.0,
        0.0,
        0.0,
        0.0,
        0.0,
        0.025,
        0.0,
        0.025,
        0.025,
        0.0,
        0.0,
        0.0,
        0.0,
        0.0,
        0.0,
        0.025,
        0.0,
        0.0,
        0.0,
        0.0,
        0.0,
        0.0,
        0.0,
        0.0,
        0.0,
        0.0,
        0.0,
        0.025,
        0.0,
        0.025,
        0.025,
        0.0,
        0.0,
        0.0,
        0.0,
        0.0,
        0.0,
        0.025,
        0.025,
        0.0,
        0.0,
        0.025,
        0.0,
        0.0,
        0.0,
        0.0,
        0.0,
        0.0,
        0.025,
        0.0,
        0.0,
        0.0,
        0.0,
        0.0,
        0.0,
        0.0,
        0.0,
        0.025,
        0.0,
        0.0,
        0.0,
        0.0,
        0.0,
        0.0,
        0.0,
        0.0,
        0.0,
        0.0,
        0.025,
        0.0,
        0.0,
        0.0,
        0.0,
        0.0,
        0.0,
        0.0,
        0.0,
        0.0,
        0.0,
        0.0,
        0.0,
        0.0,
        0.0,
        0.0,
        0.0,
        0.0,
        0.0,
        0.0,
        0.025,
        0.0,
        0.0,
        0.025,
        0.025,
        0.025,
        0.0,
        0.025,
        0.0,
        0.0,
        0.0,
        0.0,
        0.0,
        0.0,
        0.0,
        0.025,
        0.0,
        0.0,
        0.0,
        0.025,
        0.0,
        0.0,
        0.0,
        0.0,
        0.0,
        0.0,
        0.0,
        0.0,
        0.0,
        0.0,
        0.0,
        0.0,
        0.0,
        0.025,
        0.0,
        0.0,
        0.0,
        0.0,
        0.0,
        0.0,
        0.0,
        0.0,
        0.0,
        0.0,
        0.0,
        0.025,
        0.0,
        0.0,
        0.0,
        0.0,
        0.0,
        0.025,
        0.0,
        0.0,
        0.0,
        0.0,
        0.0,
        0.0,
        0.025,
        0.025,
        0.0,
        0.0,
        0.0,
        0.0,
        0.0,
        0.0,
        0.0,
        0.0,
        0.0,
        0.0,
        0.0,
        0.0,
        0.0,
        0.0,
        0.025,
        0.025,
        0.0,
        0.0,
        0.0,
        0.0,
        0.0,
        0.0,
        0.0,
        0.0,
        0.0,
        0.0,
        0.0,
        0.0,
        0.0,
        0.025,
        0.025,
        0.025,
        0.025,
        0.025,
        0.025,
        0.0,
        0.025,
        0.0,
        0.0,
        0.0,
        0.0,
        0.0,
        0.0,
        0.025,
        0.0,
        0.025,
        0.0,
        0.0,
        0.0,
        0.0,
        0.0,
        0.0,
        0.025,
        0.025,
        0.0,
        0.0,
        0.0,
        0.0,
        0.0,
        0.0,
        0.0,
        0.0,
        0.0,
        0.0,
        0.0,
        0.0,
        0.0,
        0.0,
        0.0,
        0.0,
        0.0,
        0.0,
        0.0,
        0.0,
        0.0,
        0.0,
        0.025,
        0.0,
        0.0,
        0.0,
        0.0,
        0.025,
        0.0,
        0.0,
        0.025,
        0.0,
        0.0,
        0.0,
        0.0,
        0.0,
        0.0,
        0.0,
        0.0,
        0.0,
        0.025,
        0.0,
        0.0,
        0.025,
        0.0,
        0.0,
        0.0,
        0.0,
        0.0,
        0.0,
        0.025,
        0.0,
        0.025,
        0.025,
        0.025,
        0.0,
        0.0,
        0.0,
        0.025,
        0.0,
        0.0,
        0.0,
        0.0,
        0.0,
        0.0,
        0.0,
        0.0,
        0.0,
        0.0,
        0.025,
        0.0,
        0.025,
        0.025,
        0.025,
        0.0,
        0.025,
        0.0,
        0.0,
        0.0,
        0.0,
        0.0,
        0.025,
        0.0,
        0.0,
        0.0,
        0.0,
        0.025,
        0.0,
        0.025,
        0.025,
        0.0,
        0.025,
        0.0,
        0.0,
        0.0,
        0.0,
        0.025,
        0.0,
        0.0,
        0.0,
        0.0,
        0.025,
        0.0,
        0.025,
        0.0,
        0.0,
        0.0,
        0.0,
        0.0,
        0.0,
        0.0,
        0.025,
        0.0,
        0.0,
        0.0,
        0.025,
        0.025,
        0.0,
        0.0,
        0.025,
        0.0,
        0.025,
        0.0,
        0.0,
        0.025,
        0.0,
        0.0,
        0.0,
        0.0,
        0.0,
        0.0,
        0.0,
        0.025,
        0.0,
        0.0,
        0.0,
        0.0,
        0.0,
        0.0,
        0.0,
        0.0,
        0.025,
        0.0,
        0.025,
        0.0,
        0.0,
        0.025,
        0.0,
        0.0,
        0.0,
        0.0,
        0.0,
        0.025,
        0.0,
        0.025,
        0.025,
        0.0,
        0.0,
        0.0,
        0.0,
        0.0,
        0.0,
        0.0,
        0.0,
        0.0,
        0.0,
        0.025,
        0.0,
        0.0,
        0.0,
        0.025,
        0.0,
        0.025,
        0.0,
        0.025,
        0.0,
        0.0,
        0.0,
        0.0,
        0.0,
        0.025,
        0.0,
        0.025,
        0.0,
        0.0,
        0.025,
        0.0,
        0.025,
        0.0,
        0.0,
        0.0,
        0.0,
        0.025,
        0.0,
        0.0,
        0.0,
        0.025,
        0.0,
        0.0,
        0.0,
        0.0,
        0.025,
        0.0,
        0.0,
        0.0,
        0.0,
        0.0,
        0.0,
        0.0,
        0.0,
        0.0,
        0.0,
        0.0,
        0.025,
        0.0,
        0.0,
        0.025,
        0.0,
        0.0,
        0.0,
        0.0,
        0.025,
        0.0,
        0.025,
        0.0,
        0.0,
        0.0,
        0.0,
        0.0,
        0.025,
        0.0,
        0.0,
        0.025,
        0.025,
        0.0,
        0.0,
        0.0,
        0.025,
        0.0,
        0.0,
        0.025,
        0.0,
        0.0,
        0.0,
        0.0,
        0.0,
        0.025,
        0.0,
        0.025,
        0.0,
        0.0,
        0.0,
        0.0,
        0.0,
        0.0,
        0.0,
        0.0,
        0.0,
        0.0,
        0.0,
        0.0,
        0.0,
        0.0,
        0.0,
        0.0,
        0.0,
        0.025,
        0.0,
        0.0,
        0.0,
        0.0,
        0.0,
        0.0,
        0.025,
        0.025,
        0.0,
        0.0,
        0.0,
        0.0,
        0.025,
        0.0,
        0.0,
        0.0,
        0.0,
        0.025,
        0.025,
        0.0,
        0.0,
        0.0,
        0.0,
        0.0,
        0.0,
        0.0,
        0.0,
        0.0,
        0.025,
        0.025,
        0.0,
        0.0,
        0.0,
        0.0,
        0.0,
        0.0,
        0.025,
        0.025,
        0.0,
        0.0,
        0.0,
        0.0,
        0.0,
        0.0,
        0.0,
        0.0,
        0.025,
        0.0,
        0.025,
        0.0,
        0.0,
        0.0,
        0.0,
        0.0,
        0.0,
        0.0,
        0.0,
        0.0,
        0.0,
        0.0,
        0.0,
        0.0,
        0.0,
        0.0,
        0.0,
        0.0,
        0.0,
        0.0,
        0.0,
        0.0,
        0.0,
        0.0,
        0.0,
        0.0,
        0.0,
        0.0,
        0.0,
        0.0,
        0.0,
        0.0,
        0.0,
        0.0,
        0.0,
        0.0,
        0.025,
        0.0,
        0.025,
        0.0,
        0.0,
        0.0,
        0.0,
        0.025,
        0.0,
        0.0,
        0.0,
        0.0,
        0.0,
        0.0,
        0.025,
        0.0,
        0.0,
        0.0,
        0.0,
        0.0,
        0.025,
        0.0,
        0.0,
        0.0,
        0.0,
        0.025,
        0.0,
        0.0,
        0.0,
        0.0,
        0.0,
        0.0,
        0.0,
        0.0,
        0.0,
        0.0,
        0.0,
        0.0,
        0.0,
        0.0,
        0.0,
        0.025,
        0.025,
        0.0,
        0.025,
        0.025,
        0.0,
        0.0,
        0.0,
        0.025,
        0.025,
        0.0,
        0.0,
        0.0,
        0.025,
        0.0,
        0.0,
        0.0,
        0.0,
        0.0,
        0.0,
        0.0,
        0.0,
        0.0,
        0.0,
        0.0,
        0.0,
        0.025,
        0.0,
        0.0,
        0.0,
        0.0,
        0.0,
        0.0,
        0.025,
        0.0,
        0.0,
        0.0,
        0.0,
        0.0,
        0.0,
        0.0,
        0.025,
        0.0,
        0.0,
        0.0,
        0.0,
        0.0,
        0.0,
        0.0,
        0.0,
        0.0,
        0.025,
        0.0,
        0.0,
        0.0,
        0.0,
        0.0,
        0.0,
        0.0,
        0.0,
        0.0,
        0.0,
        0.025,
        0.0,
        0.025,
        0.0,
        0.0,
        0.0,
        0.025,
        0.0,
        0.025,
        0.0,
        0.0,
        0.0,
        0.025,
        0.0,
        0.025,
        0.0,
        0.0,
        0.0,
        0.0,
        0.0,
        0.0,
        0.0,
        0.0,
        0.0,
        0.025,
        0.025,
        0.0,
        0.025,
        0.0,
        0.025,
        0.025,
        0.0,
        0.0,
        0.0,
        0.0,
        0.025,
        0.0,
        0.0,
        0.025,
        0.0,
        0.0,
        0.0,
        0.0,
        0.0,
        0.0,
        0.025,
        0.025,
        0.0,
        0.025,
        0.025,
        0.0,
        0.0,
        0.0,
        0.0,
        0.0,
        0.0,
        0.0,
        0.0,
        0.0,
        0.0,
        0.025,
        0.025,
        0.0,
        0.0,
        0.0,
        0.0,
        0.0,
        0.0,
        0.0,
        0.025,
        0.0,
        0.0,
        0.025,
        0.025,
        0.0,
        0.025,
        0.0,
        0.0,
        0.0,
        0.0,
        0.0,
        0.025,
        0.0,
        0.0,
        0.0,
        0.0,
        0.0,
        0.0,
        0.0,
        0.0,
        0.025,
        0.0,
        0.025,
        0.0,
        0.025,
        0.0,
        0.025,
        0.0,
        0.0,
        0.0,
        0.0,
        0.0,
        0.0,
        0.0,
        0.0,
        0.0,
        0.0,
        0.0,
        0.0,
        0.0,
        0.025,
        0.0,
        0.0,
        0.0,
        0.025,
        0.0,
        0.025,
        0.0,
        0.025,
        0.0,
        0.025,
        0.0,
        0.0,
        0.0,
        0.0,
        0.0,
        0.0,
        0.025,
        0.0,
        0.025,
        0.0,
        0.0,
        0.0,
        0.0,
        0.0,
        0.025,
        0.0,
        0.0,
        0.0,
        0.0,
        0.0,
        0.025,
        0.0,
        0.0,
        0.0,
        0.0,
        0.0,
        0.0,
        0.0,
        0.0,
        0.0,
        0.0,
        0.0,
        0.0,
        0.025,
        0.0,
        0.025,
        0.0,
        0.0,
        0.025,
        0.0,
        0.0,
        0.0,
        0.0,
        0.0,
        0.0,
        0.0,
        0.0,
        0.0,
        0.0,
        0.0,
        0.0,
        0.025,
        0.0,
        0.0,
        0.0,
        0.0,
        0.0,
        0.0,
        0.0,
        0.0,
        0.0,
        0.0,
        0.0,
        0.0,
        0.0,
        0.025,
        0.0,
        0.0,
        0.0,
        0.0,
        0.0,
        0.0,
        0.0,
        0.0,
        0.025,
        0.0,
        0.0,
        0.0,
        0.0,
        0.025,
        0.0,
        0.0,
        0.0,
        0.0,
        0.0,
        0.0,
        0.0,
        0.0,
        0.0,
        0.0,
        0.0,
        0.0,
        0.025,
        0.0,
        0.0,
        0.0,
        0.0,
        0.0,
        0.0,
        0.0,
        0.0,
        0.025,
        0.0,
        0.0,
        0.0,
        0.0,
        0.0,
        0.0,
        0.0,
        0.0,
        0.0,
        0.0,
        0.0,
        0.0,
        0.025,
        0.025,
        0.0,
        0.0,
        0.0,
        0.0,
        0.0,
        0.025,
        0.025,
        0.0,
        0.025,
        0.025,
        0.025,
        0.0,
        0.0,
        0.0,
        0.025,
        0.025,
        0.0,
        0.0,
        0.0,
        0.025,
        0.0,
        0.0,
        0.0,
        0.0,
        0.0,
        0.0,
        0.0,
        0.0,
        0.0,
        0.0,
        0.0,
        0.0,
        0.0,
        0.0,
        0.0,
        0.0,
        0.025,
        0.0,
        0.0,
        0.025,
        0.0,
        0.0,
        0.0,
        0.0,
        0.0,
        0.0,
        0.0,
        0.0,
        0.0,
        0.0,
        0.0,
        0.0,
        0.0,
        0.0,
        0.0,
        0.025,
        0.0,
        0.0,
        0.0,
        0.025,
        0.0,
        0.0,
        0.0,
        0.0,
        0.0,
        0.0,
        0.0,
        0.0,
        0.025,
        0.025,
        0.0,
        0.0,
        0.0,
        0.025,
        0.0,
        0.0,
        0.0,
        0.0,
        0.0,
        0.025,
        0.0,
        0.0
      ],
      "drug_rr_range": {
        "min": 0.0,
        "max": 0.013,
        "median": 0.0,
        "count": 3
      }
    },
    {
      "nct_id": "NCT01582269:Arm B: Galunisertib + Lomustine",
      "title": "A Study in Recurrent Glioblastoma (GB)",
      "drugs": [
        "LOMUSTINE",
        "GALUNISERTIB"
      ],
      "actual_response_rate": 0.013,
      "predicted_rates": [
        0.012658227848101266,
        0.0,
        0.012658227848101266,
        0.0,
        0.0,
        0.0,
        0.012658227848101266,
        0.0,
        0.0,
        0.012658227848101266,
        0.012658227848101266,
        0.012658227848101266,
        0.012658227848101266,
        0.0,
        0.012658227848101266,
        0.012658227848101266,
        0.0,
        0.0,
        0.0,
        0.012658227848101266,
        0.012658227848101266,
        0.0,
        0.0,
        0.0,
        0.0,
        0.0,
        0.0,
        0.012658227848101266,
        0.0,
        0.012658227848101266,
        0.0,
        0.0,
        0.012658227848101266,
        0.012658227848101266,
        0.012658227848101266,
        0.0,
        0.0,
        0.012658227848101266,
        0.0,
        0.0,
        0.0,
        0.0,
        0.012658227848101266,
        0.0,
        0.0,
        0.0,
        0.012658227848101266,
        0.012658227848101266,
        0.0,
        0.0,
        0.0,
        0.0,
        0.0,
        0.0,
        0.0,
        0.012658227848101266,
        0.0,
        0.012658227848101266,
        0.0,
        0.012658227848101266,
        0.012658227848101266,
        0.0,
        0.0,
        0.012658227848101266,
        0.0,
        0.012658227848101266,
        0.012658227848101266,
        0.012658227848101266,
        0.0,
        0.0,
        0.0,
        0.012658227848101266,
        0.0,
        0.0,
        0.0,
        0.0,
        0.012658227848101266,
        0.012658227848101266,
        0.0,
        0.0,
        0.0,
        0.012658227848101266,
        0.012658227848101266,
        0.0,
        0.012658227848101266,
        0.0,
        0.0,
        0.0,
        0.0,
        0.012658227848101266,
        0.012658227848101266,
        0.0,
        0.012658227848101266,
        0.012658227848101266,
        0.0,
        0.012658227848101266,
        0.0,
        0.0,
        0.0,
        0.012658227848101266,
        0.012658227848101266,
        0.0,
        0.012658227848101266,
        0.0,
        0.012658227848101266,
        0.0,
        0.012658227848101266,
        0.012658227848101266,
        0.012658227848101266,
        0.012658227848101266,
        0.0,
        0.0,
        0.0,
        0.0,
        0.012658227848101266,
        0.0,
        0.0,
        0.0,
        0.012658227848101266,
        0.0,
        0.012658227848101266,
        0.0,
        0.0,
        0.0,
        0.0,
        0.0,
        0.012658227848101266,
        0.0,
        0.012658227848101266,
        0.0,
        0.0,
        0.0,
        0.012658227848101266,
        0.0,
        0.0,
        0.012658227848101266,
        0.012658227848101266,
        0.012658227848101266,
        0.0,
        0.0,
        0.012658227848101266,
        0.012658227848101266,
        0.0,
        0.0,
        0.012658227848101266,
        0.012658227848101266,
        0.0,
        0.0,
        0.0,
        0.0,
        0.0,
        0.0,
        0.012658227848101266,
        0.0,
        0.012658227848101266,
        0.012658227848101266,
        0.0,
        0.0,
        0.012658227848101266,
        0.012658227848101266,
        0.012658227848101266,
        0.0,
        0.0,
        0.012658227848101266,
        0.0,
        0.0,
        0.0,
        0.0,
        0.0,
        0.0,
        0.0,
        0.0,
        0.0,
        0.0,
        0.0,
        0.012658227848101266,
        0.012658227848101266,
        0.0,
        0.0,
        0.0,
        0.0,
        0.0,
        0.0,
        0.0,
        0.012658227848101266,
        0.0,
        0.0,
        0.012658227848101266,
        0.0,
        0.012658227848101266,
        0.012658227848101266,
        0.012658227848101266,
        0.012658227848101266,
        0.0,
        0.012658227848101266,
        0.0,
        0.012658227848101266,
        0.0,
        0.012658227848101266,
        0.0,
        0.0,
        0.0,
        0.012658227848101266,
        0.012658227848101266,
        0.012658227848101266,
        0.012658227848101266,
        0.0,
        0.0,
        0.0,
        0.012658227848101266,
        0.012658227848101266,
        0.0,
        0.012658227848101266,
        0.0,
        0.012658227848101266,
        0.0,
        0.0,
        0.0,
        0.012658227848101266,
        0.0,
        0.012658227848101266,
        0.012658227848101266,
        0.012658227848101266,
        0.0,
        0.0,
        0.0,
        0.0,
        0.0,
        0.0,
        0.0,
        0.0,
        0.012658227848101266,
        0.0,
        0.0,
        0.0,
        0.0,
        0.0,
        0.0,
        0.012658227848101266,
        0.0,
        0.0,
        0.012658227848101266,
        0.012658227848101266,
        0.012658227848101266,
        0.0,
        0.012658227848101266,
        0.012658227848101266,
        0.012658227848101266,
        0.0,
        0.0,
        0.012658227848101266,
        0.012658227848101266,
        0.012658227848101266,
        0.012658227848101266,
        0.0,
        0.012658227848101266,
        0.0,
        0.0,
        0.0,
        0.012658227848101266,
        0.012658227848101266,
        0.0,
        0.012658227848101266,
        0.0,
        0.0,
        0.0,
        0.012658227848101266,
        0.0,
        0.0,
        0.012658227848101266,
        0.012658227848101266,
        0.012658227848101266,
        0.0,
        0.012658227848101266,
        0.0,
        0.0,
        0.0,
        0.0,
        0.0,
        0.0,
        0.0,
        0.012658227848101266,
        0.0,
        0.0,
        0.012658227848101266,
        0.0,
        0.0,
        0.0,
        0.0,
        0.0,
        0.0,
        0.0,
        0.012658227848101266,
        0.0,
        0.0,
        0.012658227848101266,
        0.0,
        0.012658227848101266,
        0.012658227848101266,
        0.0,
        0.0,
        0.012658227848101266,
        0.0,
        0.0,
        0.012658227848101266,
        0.0,
        0.0,
        0.0,
        0.0,
        0.0,
        0.012658227848101266,
        0.012658227848101266,
        0.012658227848101266,
        0.0,
        0.012658227848101266,
        0.0,
        0.0,
        0.0,
        0.012658227848101266,
        0.0,
        0.0,
        0.0,
        0.012658227848101266,
        0.0,
        0.012658227848101266,
        0.0,
        0.012658227848101266,
        0.0,
        0.0,
        0.012658227848101266,
        0.012658227848101266,
        0.0,
        0.0,
        0.0,
        0.0,
        0.0,
        0.0,
        0.0,
        0.0,
        0.012658227848101266,
        0.0,
        0.0,
        0.012658227848101266,
        0.0,
        0.0,
        0.0,
        0.0,
        0.0,
        0.0,
        0.012658227848101266,
        0.012658227848101266,
        0.0,
        0.012658227848101266,
        0.0,
        0.012658227848101266,
        0.0,
        0.0,
        0.0,
        0.0,
        0.012658227848101266,
        0.012658227848101266,
        0.012658227848101266,
        0.0,
        0.012658227848101266,
        0.0,
        0.0,
        0.0,
        0.012658227848101266,
        0.0,
        0.0,
        0.012658227848101266,
        0.012658227848101266,
        0.0,
        0.012658227848101266,
        0.012658227848101266,
        0.0,
        0.012658227848101266,
        0.0,
        0.012658227848101266,
        0.0,
        0.0,
        0.0,
        0.0,
        0.0,
        0.0,
        0.0,
        0.0,
        0.012658227848101266,
        0.0,
        0.012658227848101266,
        0.0,
        0.0,
        0.0,
        0.0,
        0.0,
        0.0,
        0.012658227848101266,
        0.012658227848101266,
        0.012658227848101266,
        0.0,
        0.0,
        0.0,
        0.0,
        0.0,
        0.012658227848101266,
        0.0,
        0.0,
        0.0,
        0.0,
        0.012658227848101266,
        0.012658227848101266,
        0.0,
        0.0,
        0.012658227848101266,
        0.012658227848101266,
        0.0,
        0.0,
        0.0,
        0.012658227848101266,
        0.0,
        0.0,
        0.012658227848101266,
        0.0,
        0.0,
        0.0,
        0.0,
        0.0,
        0.0,
        0.0,
        0.012658227848101266,
        0.0,
        0.012658227848101266,
        0.0,
        0.012658227848101266,
        0.0,
        0.0,
        0.012658227848101266,
        0.0,
        0.0,
        0.012658227848101266,
        0.0,
        0.012658227848101266,
        0.0,
        0.0,
        0.0,
        0.0,
        0.012658227848101266,
        0.0,
        0.012658227848101266,
        0.012658227848101266,
        0.0,
        0.0,
        0.0,
        0.0,
        0.0,
        0.0,
        0.0,
        0.0,
        0.0,
        0.012658227848101266,
        0.012658227848101266,
        0.0,
        0.012658227848101266,
        0.0,
        0.0,
        0.012658227848101266,
        0.0,
        0.012658227848101266,
        0.012658227848101266,
        0.0,
        0.012658227848101266,
        0.012658227848101266,
        0.012658227848101266,
        0.0,
        0.0,
        0.012658227848101266,
        0.0,
        0.0,
        0.0,
        0.0,
        0.012658227848101266,
        0.012658227848101266,
        0.0,
        0.0,
        0.012658227848101266,
        0.012658227848101266,
        0.012658227848101266,
        0.0,
        0.012658227848101266,
        0.012658227848101266,
        0.0,
        0.012658227848101266,
        0.0,
        0.0,
        0.0,
        0.012658227848101266,
        0.0,
        0.0,
        0.0,
        0.0,
        0.0,
        0.0,
        0.0,
        0.0,
        0.0,
        0.012658227848101266,
        0.012658227848101266,
        0.012658227848101266,
        0.012658227848101266,
        0.0,
        0.0,
        0.0,
        0.0,
        0.012658227848101266,
        0.0,
        0.012658227848101266,
        0.0,
        0.0,
        0.0,
        0.0,
        0.012658227848101266,
        0.0,
        0.0,
        0.0,
        0.012658227848101266,
        0.012658227848101266,
        0.012658227848101266,
        0.0,
        0.0,
        0.012658227848101266,
        0.0,
        0.0,
        0.0,
        0.012658227848101266,
        0.0,
        0.0,
        0.012658227848101266,
        0.0,
        0.012658227848101266,
        0.0,
        0.0,
        0.012658227848101266,
        0.012658227848101266,
        0.012658227848101266,
        0.012658227848101266,
        0.0,
        0.0,
        0.0,
        0.012658227848101266,
        0.0,
        0.0,
        0.012658227848101266,
        0.012658227848101266,
        0.012658227848101266,
        0.0,
        0.0,
        0.0,
        0.0,
        0.0,
        0.012658227848101266,
        0.012658227848101266,
        0.0,
        0.0,
        0.0,
        0.0,
        0.0,
        0.012658227848101266,
        0.0,
        0.0,
        0.0,
        0.0,
        0.0,
        0.0,
        0.0,
        0.012658227848101266,
        0.012658227848101266,
        0.012658227848101266,
        0.0,
        0.012658227848101266,
        0.012658227848101266,
        0.012658227848101266,
        0.0,
        0.012658227848101266,
        0.012658227848101266,
        0.012658227848101266,
        0.0,
        0.0,
        0.0,
        0.0,
        0.0,
        0.0,
        0.0,
        0.0,
        0.0,
        0.0,
        0.0,
        0.0,
        0.0,
        0.0,
        0.012658227848101266,
        0.0,
        0.0,
        0.0,
        0.0,
        0.012658227848101266,
        0.0,
        0.0,
        0.0,
        0.012658227848101266,
        0.0,
        0.0,
        0.0,
        0.012658227848101266,
        0.012658227848101266,
        0.0,
        0.0,
        0.0,
        0.0,
        0.0,
        0.0,
        0.012658227848101266,
        0.0,
        0.0,
        0.0,
        0.012658227848101266,
        0.012658227848101266,
        0.012658227848101266,
        0.0,
        0.0,
        0.0,
        0.0,
        0.012658227848101266,
        0.0,
        0.012658227848101266,
        0.0,
        0.0,
        0.0,
        0.0,
        0.0,
        0.0,
        0.0,
        0.012658227848101266,
        0.012658227848101266,
        0.012658227848101266,
        0.012658227848101266,
        0.0,
        0.012658227848101266,
        0.0,
        0.0,
        0.0,
        0.012658227848101266,
        0.0,
        0.012658227848101266,
        0.0,
        0.0,
        0.012658227848101266,
        0.0,
        0.0,
        0.0,
        0.0,
        0.0,
        0.0,
        0.012658227848101266,
        0.012658227848101266,
        0.0,
        0.012658227848101266,
        0.012658227848101266,
        0.0,
        0.0,
        0.0,
        0.0,
        0.0,
        0.012658227848101266,
        0.0,
        0.0,
        0.012658227848101266,
        0.012658227848101266,
        0.0,
        0.012658227848101266,
        0.0,
        0.0,
        0.0,
        0.0,
        0.0,
        0.0,
        0.0,
        0.012658227848101266,
        0.012658227848101266,
        0.0,
        0.0,
        0.0,
        0.0,
        0.0,
        0.0,
        0.0,
        0.0,
        0.0,
        0.0,
        0.0,
        0.0,
        0.0,
        0.0,
        0.012658227848101266,
        0.0,
        0.012658227848101266,
        0.0,
        0.012658227848101266,
        0.012658227848101266,
        0.0,
        0.012658227848101266,
        0.0,
        0.012658227848101266,
        0.0,
        0.012658227848101266,
        0.0,
        0.012658227848101266,
        0.0,
        0.012658227848101266,
        0.012658227848101266,
        0.0,
        0.012658227848101266,
        0.0,
        0.012658227848101266,
        0.0,
        0.0,
        0.012658227848101266,
        0.012658227848101266,
        0.012658227848101266,
        0.0,
        0.012658227848101266,
        0.012658227848101266,
        0.012658227848101266,
        0.0,
        0.0,
        0.012658227848101266,
        0.0,
        0.0,
        0.0,
        0.0,
        0.0,
        0.0,
        0.0,
        0.012658227848101266,
        0.0,
        0.0,
        0.012658227848101266,
        0.0,
        0.0,
        0.0,
        0.012658227848101266,
        0.0,
        0.0,
        0.0,
        0.012658227848101266,
        0.0,
        0.0,
        0.012658227848101266,
        0.0,
        0.0,
        0.012658227848101266,
        0.0,
        0.0,
        0.012658227848101266,
        0.012658227848101266,
        0.012658227848101266,
        0.012658227848101266,
        0.0,
        0.0,
        0.0,
        0.012658227848101266,
        0.012658227848101266,
        0.0,
        0.0,
        0.012658227848101266,
        0.012658227848101266,
        0.0,
        0.012658227848101266,
        0.0,
        0.012658227848101266,
        0.012658227848101266,
        0.0,
        0.0,
        0.0,
        0.0,
        0.012658227848101266,
        0.0,
        0.0,
        0.0,
        0.012658227848101266,
        0.0,
        0.0,
        0.012658227848101266,
        0.0,
        0.0,
        0.012658227848101266,
        0.012658227848101266,
        0.012658227848101266,
        0.0,
        0.0,
        0.012658227848101266,
        0.012658227848101266,
        0.0,
        0.012658227848101266,
        0.0,
        0.0,
        0.0,
        0.012658227848101266,
        0.0,
        0.012658227848101266,
        0.0,
        0.0,
        0.012658227848101266,
        0.0,
        0.0,
        0.012658227848101266,
        0.0,
        0.0,
        0.012658227848101266,
        0.0,
        0.0,
        0.0,
        0.012658227848101266,
        0.0,
        0.0,
        0.0,
        0.012658227848101266,
        0.0,
        0.0,
        0.0,
        0.0,
        0.0,
        0.0,
        0.0,
        0.012658227848101266,
        0.012658227848101266,
        0.0,
        0.0,
        0.012658227848101266,
        0.012658227848101266,
        0.0,
        0.0,
        0.0,
        0.0,
        0.0,
        0.0,
        0.0,
        0.012658227848101266,
        0.0,
        0.012658227848101266,
        0.012658227848101266,
        0.012658227848101266,
        0.0,
        0.0,
        0.0,
        0.0,
        0.012658227848101266,
        0.012658227848101266,
        0.012658227848101266,
        0.012658227848101266,
        0.0,
        0.0,
        0.0,
        0.012658227848101266,
        0.012658227848101266,
        0.0,
        0.0,
        0.0,
        0.0,
        0.0,
        0.0,
        0.012658227848101266,
        0.0,
        0.0,
        0.0,
        0.0,
        0.0,
        0.0,
        0.0,
        0.0,
        0.012658227848101266,
        0.0,
        0.0,
        0.0,
        0.0,
        0.0,
        0.0,
        0.0,
        0.0,
        0.0,
        0.0,
        0.012658227848101266,
        0.0,
        0.012658227848101266,
        0.0,
        0.0,
        0.012658227848101266,
        0.0,
        0.012658227848101266,
        0.0,
        0.0,
        0.0,
        0.0,
        0.012658227848101266,
        0.012658227848101266,
        0.012658227848101266,
        0.0,
        0.0,
        0.0,
        0.012658227848101266,
        0.0,
        0.0,
        0.012658227848101266,
        0.0,
        0.0,
        0.0,
        0.012658227848101266,
        0.0,
        0.012658227848101266,
        0.0,
        0.012658227848101266,
        0.012658227848101266,
        0.012658227848101266,
        0.0,
        0.012658227848101266,
        0.012658227848101266,
        0.012658227848101266,
        0.0,
        0.0,
        0.0,
        0.0,
        0.012658227848101266,
        0.0,
        0.0,
        0.012658227848101266,
        0.012658227848101266,
        0.0,
        0.0,
        0.0,
        0.0,
        0.012658227848101266,
        0.012658227848101266,
        0.0,
        0.0,
        0.012658227848101266,
        0.012658227848101266,
        0.0,
        0.0,
        0.0,
        0.012658227848101266,
        0.0,
        0.0,
        0.0,
        0.0,
        0.012658227848101266,
        0.012658227848101266,
        0.0,
        0.0,
        0.012658227848101266,
        0.0,
        0.0,
        0.0,
        0.0,
        0.012658227848101266,
        0.012658227848101266,
        0.0,
        0.012658227848101266,
        0.0,
        0.012658227848101266,
        0.0,
        0.0,
        0.0,
        0.012658227848101266,
        0.0,
        0.0,
        0.0,
        0.012658227848101266,
        0.0,
        0.0,
        0.0,
        0.0,
        0.0,
        0.0,
        0.0,
        0.012658227848101266,
        0.012658227848101266,
        0.012658227848101266,
        0.012658227848101266,
        0.012658227848101266,
        0.012658227848101266,
        0.0,
        0.012658227848101266,
        0.0,
        0.0,
        0.0,
        0.012658227848101266,
        0.012658227848101266,
        0.012658227848101266,
        0.0,
        0.0,
        0.012658227848101266
      ],
      "drug_rr_range": {
        "min": 0.0,
        "max": 0.013,
        "median": 0.0,
        "count": 3
      }
    }
  ],
  "excluded_trials": [],
  "analyses": {
    "mae": {
      "value": 0.0066,
      "per_trial": [
        {
          "nct_id": "NCT01582269:Arm C: Lomustine + Placebo",
          "actual": 0.0,
          "predicted": 0.004775000000000001,
          "abs_error": 0.004775000000000001
        },
        {
          "nct_id": "NCT01582269:Arm B: Galunisertib + Lomustine",
          "actual": 0.013,
          "predicted": 0.004582278481012659,
          "abs_error": 0.00841772151898734
        }
      ]
    },
    "bland_altman": {
      "mean_diff": -0.0018,
      "std_diff": 0.0093,
      "upper_loa": 0.0165,
      "lower_loa": -0.0201,
      "points": [
        {
          "nct_id": "NCT01582269:Arm C: Lomustine + Placebo",
          "mean": 0.0023875000000000003,
          "diff": 0.004775000000000001
        },
        {
          "nct_id": "NCT01582269:Arm B: Galunisertib + Lomustine",
          "mean": 0.00879113924050633,
          "diff": -0.00841772151898734
        }
      ]
    },
    "ci_coverage": {
      "coverage_rate": 0.5,
      "covered_count": 1,
      "total_trials": 2,
      "trials": [
        {
          "nct_id": "NCT01582269:Arm C: Lomustine + Placebo",
          "actual": 0.0,
          "ci_lower": 0.0,
          "ci_upper": 0.025,
          "covered": true,
          "predicted_mean": 0.004775000000000001
        },
        {
          "nct_id": "NCT01582269:Arm B: Galunisertib + Lomustine",
          "actual": 0.013,
          "ci_lower": 0.0,
          "ci_upper": 0.0127,
          "covered": false,
          "predicted_mean": 0.004582278481012659
        }
      ]
    }
  },
  "responder_classification_matrix": {
    "trials": [
      "NCT01582269:Arm A: Galunisertib",
      "NCT01582269:Arm B: Galunisertib + Lomustine",
      "NCT01582269:Arm C: Lomustine + Placebo"
    ],
    "patients": {
      "TCGA-06-0190-02": {
        "NCT01582269:Arm A: Galunisertib": false,
        "NCT01582269:Arm B: Galunisertib + Lomustine": false,
        "NCT01582269:Arm C: Lomustine + Placebo": false
      },
      "TCGA-19-4065-01": {
        "NCT01582269:Arm A: Galunisertib": false,
        "NCT01582269:Arm B: Galunisertib + Lomustine": false,
        "NCT01582269:Arm C: Lomustine + Placebo": false
      },
      "TCGA-19-4065-02": {
        "NCT01582269:Arm A: Galunisertib": false,
        "NCT01582269:Arm B: Galunisertib + Lomustine": false,
        "NCT01582269:Arm C: Lomustine + Placebo": false
      },
      "TCGA-14-1034-02": {
        "NCT01582269:Arm A: Galunisertib": false,
        "NCT01582269:Arm B: Galunisertib + Lomustine": false,
        "NCT01582269:Arm C: Lomustine + Placebo": false
      },
      "TCGA-06-0211-02": {
        "NCT01582269:Arm A: Galunisertib": false,
        "NCT01582269:Arm B: Galunisertib + Lomustine": false,
        "NCT01582269:Arm C: Lomustine + Placebo": false
      },
      "TCGA-06-0686-01": {
        "NCT01582269:Arm A: Galunisertib": false,
        "NCT01582269:Arm B: Galunisertib + Lomustine": false,
        "NCT01582269:Arm C: Lomustine + Placebo": false
      },
      "TCGA-76-4931-01": {
        "NCT01582269:Arm A: Galunisertib": false,
        "NCT01582269:Arm B: Galunisertib + Lomustine": false,
        "NCT01582269:Arm C: Lomustine + Placebo": false
      },
      "TCGA-06-0211-01": {
        "NCT01582269:Arm A: Galunisertib": false,
        "NCT01582269:Arm B: Galunisertib + Lomustine": false,
        "NCT01582269:Arm C: Lomustine + Placebo": false
      },
      "TCGA-14-1402-01": {
        "NCT01582269:Arm A: Galunisertib": false,
        "NCT01582269:Arm B: Galunisertib + Lomustine": false,
        "NCT01582269:Arm C: Lomustine + Placebo": false
      },
      "TCGA-14-0789-01": {
        "NCT01582269:Arm A: Galunisertib": true,
        "NCT01582269:Arm B: Galunisertib + Lomustine": false,
        "NCT01582269:Arm C: Lomustine + Placebo": false
      },
      "TCGA-06-0644-01": {
        "NCT01582269:Arm A: Galunisertib": false,
        "NCT01582269:Arm B: Galunisertib + Lomustine": false,
        "NCT01582269:Arm C: Lomustine + Placebo": false
      },
      "TCGA-06-0744-01": {
        "NCT01582269:Arm A: Galunisertib": false,
        "NCT01582269:Arm B: Galunisertib + Lomustine": false,
        "NCT01582269:Arm C: Lomustine + Placebo": false
      },
      "TCGA-16-1045-01": {
        "NCT01582269:Arm A: Galunisertib": true,
        "NCT01582269:Arm B: Galunisertib + Lomustine": false,
        "NCT01582269:Arm C: Lomustine + Placebo": false
      },
      "TCGA-06-0174-01": {
        "NCT01582269:Arm A: Galunisertib": false,
        "NCT01582269:Arm B: Galunisertib + Lomustine": false,
        "NCT01582269:Arm C: Lomustine + Placebo": false
      },
      "TCGA-28-5215-01": {
        "NCT01582269:Arm A: Galunisertib": false,
        "NCT01582269:Arm B: Galunisertib + Lomustine": false,
        "NCT01582269:Arm C: Lomustine + Placebo": false
      },
      "TCGA-19-1389-01": {
        "NCT01582269:Arm A: Galunisertib": false,
        "NCT01582269:Arm B: Galunisertib + Lomustine": false,
        "NCT01582269:Arm C: Lomustine + Placebo": false
      },
      "TCGA-06-0221-01": {
        "NCT01582269:Arm A: Galunisertib": false,
        "NCT01582269:Arm B: Galunisertib + Lomustine": false,
        "NCT01582269:Arm C: Lomustine + Placebo": false
      },
      "TCGA-12-3653-01": {
        "NCT01582269:Arm A: Galunisertib": false,
        "NCT01582269:Arm B: Galunisertib + Lomustine": false,
        "NCT01582269:Arm C: Lomustine + Placebo": false
      },
      "TCGA-06-0129-01": {
        "NCT01582269:Arm A: Galunisertib": true,
        "NCT01582269:Arm B: Galunisertib + Lomustine": true,
        "NCT01582269:Arm C: Lomustine + Placebo": true
      },
      "TCGA-76-4927-01": {
        "NCT01582269:Arm A: Galunisertib": false,
        "NCT01582269:Arm B: Galunisertib + Lomustine": false,
        "NCT01582269:Arm C: Lomustine + Placebo": false
      },
      "TCGA-12-1597-01": {
        "NCT01582269:Arm A: Galunisertib": false,
        "NCT01582269:Arm B: Galunisertib + Lomustine": false,
        "NCT01582269:Arm C: Lomustine + Placebo": false
      },
      "TCGA-12-5295-01": {
        "NCT01582269:Arm A: Galunisertib": false,
        "NCT01582269:Arm B: Galunisertib + Lomustine": false,
        "NCT01582269:Arm C: Lomustine + Placebo": false
      },
      "TCGA-14-0736-01": {
        "NCT01582269:Arm A: Galunisertib": false,
        "NCT01582269:Arm B: Galunisertib + Lomustine": false,
        "NCT01582269:Arm C: Lomustine + Placebo": false
      },
      "TCGA-27-2528-01": {
        "NCT01582269:Arm A: Galunisertib": false,
        "NCT01582269:Arm B: Galunisertib + Lomustine": false,
        "NCT01582269:Arm C: Lomustine + Placebo": false
      },
      "TCGA-76-4932-01": {
        "NCT01582269:Arm A: Galunisertib": false,
        "NCT01582269:Arm B: Galunisertib + Lomustine": false,
        "NCT01582269:Arm C: Lomustine + Placebo": false
      },
      "TCGA-06-0138-01": {
        "NCT01582269:Arm A: Galunisertib": false,
        "NCT01582269:Arm B: Galunisertib + Lomustine": false,
        "NCT01582269:Arm C: Lomustine + Placebo": false
      },
      "TCGA-26-5133-01": {
        "NCT01582269:Arm A: Galunisertib": false,
        "NCT01582269:Arm B: Galunisertib + Lomustine": false,
        "NCT01582269:Arm C: Lomustine + Placebo": false
      },
      "TCGA-06-5414-01": {
        "NCT01582269:Arm A: Galunisertib": false,
        "NCT01582269:Arm B: Galunisertib + Lomustine": false,
        "NCT01582269:Arm C: Lomustine + Placebo": false
      },
      "TCGA-32-5222-01": {
        "NCT01582269:Arm A: Galunisertib": false,
        "NCT01582269:Arm B: Galunisertib + Lomustine": false,
        "NCT01582269:Arm C: Lomustine + Placebo": false
      },
      "TCGA-06-5411-01": {
        "NCT01582269:Arm A: Galunisertib": false,
        "NCT01582269:Arm B: Galunisertib + Lomustine": false,
        "NCT01582269:Arm C: Lomustine + Placebo": false
      },
      "TCGA-27-2523-01": {
        "NCT01582269:Arm A: Galunisertib": false,
        "NCT01582269:Arm B: Galunisertib + Lomustine": false,
        "NCT01582269:Arm C: Lomustine + Placebo": false
      },
      "TCGA-14-1034-01": {
        "NCT01582269:Arm A: Galunisertib": false,
        "NCT01582269:Arm B: Galunisertib + Lomustine": false,
        "NCT01582269:Arm C: Lomustine + Placebo": false
      },
      "TCGA-06-0878-01": {
        "NCT01582269:Arm A: Galunisertib": true,
        "NCT01582269:Arm B: Galunisertib + Lomustine": false,
        "NCT01582269:Arm C: Lomustine + Placebo": false
      },
      "TCGA-06-0178-01": {
        "NCT01582269:Arm A: Galunisertib": false,
        "NCT01582269:Arm B: Galunisertib + Lomustine": false,
        "NCT01582269:Arm C: Lomustine + Placebo": false
      },
      "TCGA-41-3915-01": {
        "NCT01582269:Arm A: Galunisertib": false,
        "NCT01582269:Arm B: Galunisertib + Lomustine": false,
        "NCT01582269:Arm C: Lomustine + Placebo": false
      },
      "TCGA-06-0190-01": {
        "NCT01582269:Arm A: Galunisertib": false,
        "NCT01582269:Arm B: Galunisertib + Lomustine": false,
        "NCT01582269:Arm C: Lomustine + Placebo": false
      },
      "TCGA-41-5651-01": {
        "NCT01582269:Arm A: Galunisertib": false,
        "NCT01582269:Arm B: Galunisertib + Lomustine": false,
        "NCT01582269:Arm C: Lomustine + Placebo": false
      },
      "TCGA-76-4926-01": {
        "NCT01582269:Arm A: Galunisertib": false,
        "NCT01582269:Arm B: Galunisertib + Lomustine": false,
        "NCT01582269:Arm C: Lomustine + Placebo": false
      },
      "TCGA-06-0152-01": {
        "NCT01582269:Arm A: Galunisertib": false,
        "NCT01582269:Arm B: Galunisertib + Lomustine": false,
        "NCT01582269:Arm C: Lomustine + Placebo": false
      },
      "TCGA-27-1831-01": {
        "NCT01582269:Arm A: Galunisertib": false,
        "NCT01582269:Arm B: Galunisertib + Lomustine": false,
        "NCT01582269:Arm C: Lomustine + Placebo": false
      },
      "TCGA-27-1830-01": {
        "NCT01582269:Arm A: Galunisertib": false,
        "NCT01582269:Arm B: Galunisertib + Lomustine": false,
        "NCT01582269:Arm C: Lomustine + Placebo": false
      },
      "TCGA-06-0158-01": {
        "NCT01582269:Arm A: Galunisertib": true,
        "NCT01582269:Arm B: Galunisertib + Lomustine": false,
        "NCT01582269:Arm C: Lomustine + Placebo": false
      },
      "TCGA-12-3650-01": {
        "NCT01582269:Arm A: Galunisertib": false,
        "NCT01582269:Arm B: Galunisertib + Lomustine": false,
        "NCT01582269:Arm C: Lomustine + Placebo": false
      },
      "TCGA-15-0742-01": {
        "NCT01582269:Arm A: Galunisertib": false,
        "NCT01582269:Arm B: Galunisertib + Lomustine": false,
        "NCT01582269:Arm C: Lomustine + Placebo": false
      },
      "TCGA-06-2565-01": {
        "NCT01582269:Arm A: Galunisertib": false,
        "NCT01582269:Arm B: Galunisertib + Lomustine": false,
        "NCT01582269:Arm C: Lomustine + Placebo": false
      },
      "TCGA-32-1970-01": {
        "NCT01582269:Arm A: Galunisertib": false,
        "NCT01582269:Arm B: Galunisertib + Lomustine": false,
        "NCT01582269:Arm C: Lomustine + Placebo": false
      },
      "TCGA-06-5408-01": {
        "NCT01582269:Arm A: Galunisertib": false,
        "NCT01582269:Arm B: Galunisertib + Lomustine": false,
        "NCT01582269:Arm C: Lomustine + Placebo": false
      },
      "TCGA-06-0745-01": {
        "NCT01582269:Arm A: Galunisertib": false,
        "NCT01582269:Arm B: Galunisertib + Lomustine": false,
        "NCT01582269:Arm C: Lomustine + Placebo": false
      },
      "TCGA-19-1787-01": {
        "NCT01582269:Arm A: Galunisertib": false,
        "NCT01582269:Arm B: Galunisertib + Lomustine": false,
        "NCT01582269:Arm C: Lomustine + Placebo": false
      },
      "TCGA-32-4213-01": {
        "NCT01582269:Arm A: Galunisertib": false,
        "NCT01582269:Arm B: Galunisertib + Lomustine": false,
        "NCT01582269:Arm C: Lomustine + Placebo": false
      },
      "TCGA-28-5208-01": {
        "NCT01582269:Arm A: Galunisertib": false,
        "NCT01582269:Arm B: Galunisertib + Lomustine": false,
        "NCT01582269:Arm C: Lomustine + Placebo": false
      },
      "TCGA-06-5858-01": {
        "NCT01582269:Arm A: Galunisertib": false,
        "NCT01582269:Arm B: Galunisertib + Lomustine": false,
        "NCT01582269:Arm C: Lomustine + Placebo": false
      },
      "TCGA-02-2485-01": {
        "NCT01582269:Arm A: Galunisertib": false,
        "NCT01582269:Arm B: Galunisertib + Lomustine": false,
        "NCT01582269:Arm C: Lomustine + Placebo": false
      },
      "TCGA-06-0141-01": {
        "NCT01582269:Arm A: Galunisertib": false,
        "NCT01582269:Arm B: Galunisertib + Lomustine": false,
        "NCT01582269:Arm C: Lomustine + Placebo": false
      },
      "TCGA-06-2561-01": {
        "NCT01582269:Arm A: Galunisertib": false,
        "NCT01582269:Arm B: Galunisertib + Lomustine": false,
        "NCT01582269:Arm C: Lomustine + Placebo": false
      },
      "TCGA-32-2616-01": {
        "NCT01582269:Arm A: Galunisertib": false,
        "NCT01582269:Arm B: Galunisertib + Lomustine": false,
        "NCT01582269:Arm C: Lomustine + Placebo": false
      },
      "TCGA-06-2562-01": {
        "NCT01582269:Arm A: Galunisertib": false,
        "NCT01582269:Arm B: Galunisertib + Lomustine": false,
        "NCT01582269:Arm C: Lomustine + Placebo": false
      },
      "TCGA-02-0060-01": {
        "NCT01582269:Arm A: Galunisertib": true,
        "NCT01582269:Arm B: Galunisertib + Lomustine": false,
        "NCT01582269:Arm C: Lomustine + Placebo": false
      },
      "TCGA-06-0137-01": {
        "NCT01582269:Arm A: Galunisertib": false,
        "NCT01582269:Arm B: Galunisertib + Lomustine": false,
        "NCT01582269:Arm C: Lomustine + Placebo": false
      },
      "TCGA-76-6193-01": {
        "NCT01582269:Arm A: Galunisertib": true,
        "NCT01582269:Arm B: Galunisertib + Lomustine": false,
        "NCT01582269:Arm C: Lomustine + Placebo": false
      },
      "TCGA-15-1449-01": {
        "NCT01582269:Arm A: Galunisertib": false,
        "NCT01582269:Arm B: Galunisertib + Lomustine": false,
        "NCT01582269:Arm C: Lomustine + Placebo": false
      },
      "TCGA-28-5214-01": {
        "NCT01582269:Arm A: Galunisertib": false,
        "NCT01582269:Arm B: Galunisertib + Lomustine": false,
        "NCT01582269:Arm C: Lomustine + Placebo": false
      },
      "TCGA-02-0099-01": {
        "NCT01582269:Arm A: Galunisertib": false,
        "NCT01582269:Arm B: Galunisertib + Lomustine": false,
        "NCT01582269:Arm C: Lomustine + Placebo": false
      },
      "TCGA-12-1096-01": {
        "NCT01582269:Arm A: Galunisertib": false,
        "NCT01582269:Arm B: Galunisertib + Lomustine": false,
        "NCT01582269:Arm C: Lomustine + Placebo": false
      },
      "TCGA-06-0881-01": {
        "NCT01582269:Arm A: Galunisertib": true,
        "NCT01582269:Arm B: Galunisertib + Lomustine": false,
        "NCT01582269:Arm C: Lomustine + Placebo": false
      },
      "TCGA-06-1802-01": {
        "NCT01582269:Arm A: Galunisertib": false,
        "NCT01582269:Arm B: Galunisertib + Lomustine": false,
        "NCT01582269:Arm C: Lomustine + Placebo": false
      },
      "TCGA-02-0083-01": {
        "NCT01582269:Arm A: Galunisertib": false,
        "NCT01582269:Arm B: Galunisertib + Lomustine": false,
        "NCT01582269:Arm C: Lomustine + Placebo": false
      },
      "TCGA-02-0069-01": {
        "NCT01582269:Arm A: Galunisertib": false,
        "NCT01582269:Arm B: Galunisertib + Lomustine": false,
        "NCT01582269:Arm C: Lomustine + Placebo": false
      },
      "TCGA-02-0289-01": {
        "NCT01582269:Arm A: Galunisertib": false,
        "NCT01582269:Arm B: Galunisertib + Lomustine": false,
        "NCT01582269:Arm C: Lomustine + Placebo": false
      },
      "TCGA-19-5959-01": {
        "NCT01582269:Arm A: Galunisertib": false,
        "NCT01582269:Arm B: Galunisertib + Lomustine": false,
        "NCT01582269:Arm C: Lomustine + Placebo": false
      },
      "TCGA-15-1447-01": {
        "NCT01582269:Arm A: Galunisertib": false,
        "NCT01582269:Arm B: Galunisertib + Lomustine": false,
        "NCT01582269:Arm C: Lomustine + Placebo": false
      },
      "TCGA-08-0244-01": {
        "NCT01582269:Arm A: Galunisertib": false,
        "NCT01582269:Arm B: Galunisertib + Lomustine": false,
        "NCT01582269:Arm C: Lomustine + Placebo": false
      },
      "TCGA-12-0688-01": {
        "NCT01582269:Arm A: Galunisertib": false,
        "NCT01582269:Arm B: Galunisertib + Lomustine": false,
        "NCT01582269:Arm C: Lomustine + Placebo": false
      },
      "TCGA-02-0115-01": {
        "NCT01582269:Arm A: Galunisertib": false,
        "NCT01582269:Arm B: Galunisertib + Lomustine": false,
        "NCT01582269:Arm C: Lomustine + Placebo": false
      },
      "TCGA-08-0360-01": {
        "NCT01582269:Arm A: Galunisertib": false,
        "NCT01582269:Arm B: Galunisertib + Lomustine": false,
        "NCT01582269:Arm C: Lomustine + Placebo": false
      },
      "TCGA-26-1440-01": {
        "NCT01582269:Arm A: Galunisertib": false,
        "NCT01582269:Arm B: Galunisertib + Lomustine": false,
        "NCT01582269:Arm C: Lomustine + Placebo": false
      },
      "TCGA-14-1459-01": {
        "NCT01582269:Arm A: Galunisertib": false,
        "NCT01582269:Arm B: Galunisertib + Lomustine": false,
        "NCT01582269:Arm C: Lomustine + Placebo": false
      },
      "TCGA-12-0692-01": {
        "NCT01582269:Arm A: Galunisertib": false,
        "NCT01582269:Arm B: Galunisertib + Lomustine": false,
        "NCT01582269:Arm C: Lomustine + Placebo": false
      },
      "TCGA-12-3646-01": {
        "NCT01582269:Arm A: Galunisertib": false,
        "NCT01582269:Arm B: Galunisertib + Lomustine": false,
        "NCT01582269:Arm C: Lomustine + Placebo": false
      },
      "TCGA-02-0338-01": {
        "NCT01582269:Arm A: Galunisertib": false,
        "NCT01582269:Arm B: Galunisertib + Lomustine": false,
        "NCT01582269:Arm C: Lomustine + Placebo": false
      },
      "TCGA-06-0206-01": {
        "NCT01582269:Arm A: Galunisertib": false,
        "NCT01582269:Arm B: Galunisertib + Lomustine": false,
        "NCT01582269:Arm C: Lomustine + Placebo": false
      },
      "TCGA-02-0023-01": {
        "NCT01582269:Arm A: Galunisertib": false,
        "NCT01582269:Arm B: Galunisertib + Lomustine": false,
        "NCT01582269:Arm C: Lomustine + Placebo": false
      },
      "TCGA-12-1098-01": {
        "NCT01582269:Arm A: Galunisertib": false,
        "NCT01582269:Arm B: Galunisertib + Lomustine": false,
        "NCT01582269:Arm C: Lomustine + Placebo": false
      },
      "TCGA-02-0330-01": {
        "NCT01582269:Arm A: Galunisertib": false,
        "NCT01582269:Arm B: Galunisertib + Lomustine": false,
        "NCT01582269:Arm C: Lomustine + Placebo": false
      },
      "TCGA-02-0440-01": {
        "NCT01582269:Arm A: Galunisertib": false,
        "NCT01582269:Arm B: Galunisertib + Lomustine": false,
        "NCT01582269:Arm C: Lomustine + Placebo": false
      },
      "TCGA-12-3648-01": {
        "NCT01582269:Arm A: Galunisertib": false,
        "NCT01582269:Arm B: Galunisertib + Lomustine": false,
        "NCT01582269:Arm C: Lomustine + Placebo": false
      },
      "TCGA-02-0001-01": {
        "NCT01582269:Arm A: Galunisertib": false,
        "NCT01582269:Arm B: Galunisertib + Lomustine": false,
        "NCT01582269:Arm C: Lomustine + Placebo": false
      },
      "TCGA-26-1439-01": {
        "NCT01582269:Arm A: Galunisertib": false,
        "NCT01582269:Arm B: Galunisertib + Lomustine": false,
        "NCT01582269:Arm C: Lomustine + Placebo": false
      },
      "TCGA-02-0004-01": {
        "NCT01582269:Arm A: Galunisertib": false,
        "NCT01582269:Arm B: Galunisertib + Lomustine": false,
        "NCT01582269:Arm C: Lomustine + Placebo": false
      },
      "TCGA-12-1094-01": {
        "NCT01582269:Arm A: Galunisertib": false,
        "NCT01582269:Arm B: Galunisertib + Lomustine": false,
        "NCT01582269:Arm C: Lomustine + Placebo": false
      },
      "TCGA-06-0214-01": {
        "NCT01582269:Arm A: Galunisertib": false,
        "NCT01582269:Arm B: Galunisertib + Lomustine": false,
        "NCT01582269:Arm C: Lomustine + Placebo": false
      },
      "TCGA-19-1387-01": {
        "NCT01582269:Arm A: Galunisertib": false,
        "NCT01582269:Arm B: Galunisertib + Lomustine": false,
        "NCT01582269:Arm C: Lomustine + Placebo": false
      },
      "TCGA-32-1986-01": {
        "NCT01582269:Arm A: Galunisertib": false,
        "NCT01582269:Arm B: Galunisertib + Lomustine": false,
        "NCT01582269:Arm C: Lomustine + Placebo": false
      },
      "TCGA-12-0654-01": {
        "NCT01582269:Arm A: Galunisertib": false,
        "NCT01582269:Arm B: Galunisertib + Lomustine": false,
        "NCT01582269:Arm C: Lomustine + Placebo": false
      },
      "TCGA-32-1979-01": {
        "NCT01582269:Arm A: Galunisertib": true,
        "NCT01582269:Arm B: Galunisertib + Lomustine": false,
        "NCT01582269:Arm C: Lomustine + Placebo": false
      },
      "TCGA-02-0048-01": {
        "NCT01582269:Arm A: Galunisertib": false,
        "NCT01582269:Arm B: Galunisertib + Lomustine": false,
        "NCT01582269:Arm C: Lomustine + Placebo": false
      },
      "TCGA-06-0146-01": {
        "NCT01582269:Arm A: Galunisertib": false,
        "NCT01582269:Arm B: Galunisertib + Lomustine": false,
        "NCT01582269:Arm C: Lomustine + Placebo": false
      },
      "TCGA-15-1446-01": {
        "NCT01582269:Arm A: Galunisertib": false,
        "NCT01582269:Arm B: Galunisertib + Lomustine": false,
        "NCT01582269:Arm C: Lomustine + Placebo": false
      },
      "TCGA-26-1438-01": {
        "NCT01582269:Arm A: Galunisertib": false,
        "NCT01582269:Arm B: Galunisertib + Lomustine": false,
        "NCT01582269:Arm C: Lomustine + Placebo": false
      },
      "TCGA-12-0772-01": {
        "NCT01582269:Arm A: Galunisertib": false,
        "NCT01582269:Arm B: Galunisertib + Lomustine": false,
        "NCT01582269:Arm C: Lomustine + Placebo": false
      },
      "TCGA-02-0104-01": {
        "NCT01582269:Arm A: Galunisertib": false,
        "NCT01582269:Arm B: Galunisertib + Lomustine": false,
        "NCT01582269:Arm C: Lomustine + Placebo": false
      },
      "TCGA-06-0409-01": {
        "NCT01582269:Arm A: Galunisertib": true,
        "NCT01582269:Arm B: Galunisertib + Lomustine": false,
        "NCT01582269:Arm C: Lomustine + Placebo": false
      },
      "TCGA-02-0052-01": {
        "NCT01582269:Arm A: Galunisertib": false,
        "NCT01582269:Arm B: Galunisertib + Lomustine": false,
        "NCT01582269:Arm C: Lomustine + Placebo": false
      },
      "TCGA-12-1095-01": {
        "NCT01582269:Arm A: Galunisertib": false,
        "NCT01582269:Arm B: Galunisertib + Lomustine": false,
        "NCT01582269:Arm C: Lomustine + Placebo": false
      },
      "TCGA-12-1093-01": {
        "NCT01582269:Arm A: Galunisertib": false,
        "NCT01582269:Arm B: Galunisertib + Lomustine": false,
        "NCT01582269:Arm C: Lomustine + Placebo": false
      },
      "TCGA-27-2518-01": {
        "NCT01582269:Arm A: Galunisertib": false,
        "NCT01582269:Arm B: Galunisertib + Lomustine": false,
        "NCT01582269:Arm C: Lomustine + Placebo": false
      },
      "TCGA-12-1099-01": {
        "NCT01582269:Arm A: Galunisertib": false,
        "NCT01582269:Arm B: Galunisertib + Lomustine": false,
        "NCT01582269:Arm C: Lomustine + Placebo": false
      },
      "TCGA-02-0028-01": {
        "NCT01582269:Arm A: Galunisertib": true,
        "NCT01582269:Arm B: Galunisertib + Lomustine": false,
        "NCT01582269:Arm C: Lomustine + Placebo": false
      },
      "TCGA-02-2470-01": {
        "NCT01582269:Arm A: Galunisertib": false,
        "NCT01582269:Arm B: Galunisertib + Lomustine": false,
        "NCT01582269:Arm C: Lomustine + Placebo": false
      },
      "TCGA-02-0439-01": {
        "NCT01582269:Arm A: Galunisertib": false,
        "NCT01582269:Arm B: Galunisertib + Lomustine": false,
        "NCT01582269:Arm C: Lomustine + Placebo": false
      },
      "TCGA-16-1055-01": {
        "NCT01582269:Arm A: Galunisertib": false,
        "NCT01582269:Arm B: Galunisertib + Lomustine": false,
        "NCT01582269:Arm C: Lomustine + Placebo": false
      },
      "TCGA-02-0114-01": {
        "NCT01582269:Arm A: Galunisertib": false,
        "NCT01582269:Arm B: Galunisertib + Lomustine": false,
        "NCT01582269:Arm C: Lomustine + Placebo": false
      },
      "TCGA-12-0829-01": {
        "NCT01582269:Arm A: Galunisertib": false,
        "NCT01582269:Arm B: Galunisertib + Lomustine": false,
        "NCT01582269:Arm C: Lomustine + Placebo": false
      },
      "TCGA-02-0003-01": {
        "NCT01582269:Arm A: Galunisertib": false,
        "NCT01582269:Arm B: Galunisertib + Lomustine": false,
        "NCT01582269:Arm C: Lomustine + Placebo": false
      },
      "TCGA-02-0321-01": {
        "NCT01582269:Arm A: Galunisertib": false,
        "NCT01582269:Arm B: Galunisertib + Lomustine": false,
        "NCT01582269:Arm C: Lomustine + Placebo": false
      },
      "TCGA-02-0087-01": {
        "NCT01582269:Arm A: Galunisertib": false,
        "NCT01582269:Arm B: Galunisertib + Lomustine": false,
        "NCT01582269:Arm C: Lomustine + Placebo": false
      },
      "TCGA-06-0166-01": {
        "NCT01582269:Arm A: Galunisertib": false,
        "NCT01582269:Arm B: Galunisertib + Lomustine": false,
        "NCT01582269:Arm C: Lomustine + Placebo": false
      },
      "TCGA-76-4935-01": {
        "NCT01582269:Arm A: Galunisertib": false,
        "NCT01582269:Arm B: Galunisertib + Lomustine": false,
        "NCT01582269:Arm C: Lomustine + Placebo": false
      },
      "TCGA-19-5958-01": {
        "NCT01582269:Arm A: Galunisertib": false,
        "NCT01582269:Arm B: Galunisertib + Lomustine": false,
        "NCT01582269:Arm C: Lomustine + Placebo": false
      },
      "TCGA-32-4209-01": {
        "NCT01582269:Arm A: Galunisertib": false,
        "NCT01582269:Arm B: Galunisertib + Lomustine": false,
        "NCT01582269:Arm C: Lomustine + Placebo": false
      },
      "TCGA-76-6191-01": {
        "NCT01582269:Arm A: Galunisertib": false,
        "NCT01582269:Arm B: Galunisertib + Lomustine": false,
        "NCT01582269:Arm C: Lomustine + Placebo": false
      },
      "TCGA-02-0057-01": {
        "NCT01582269:Arm A: Galunisertib": false,
        "NCT01582269:Arm B: Galunisertib + Lomustine": false,
        "NCT01582269:Arm C: Lomustine + Placebo": false
      },
      "TCGA-32-2491-01": {
        "NCT01582269:Arm A: Galunisertib": false,
        "NCT01582269:Arm B: Galunisertib + Lomustine": false,
        "NCT01582269:Arm C: Lomustine + Placebo": false
      },
      "TCGA-02-2466-01": {
        "NCT01582269:Arm A: Galunisertib": false,
        "NCT01582269:Arm B: Galunisertib + Lomustine": false,
        "NCT01582269:Arm C: Lomustine + Placebo": false
      },
      "TCGA-08-0518-01": {
        "NCT01582269:Arm A: Galunisertib": false,
        "NCT01582269:Arm B: Galunisertib + Lomustine": false,
        "NCT01582269:Arm C: Lomustine + Placebo": false
      },
      "TCGA-06-0241-01": {
        "NCT01582269:Arm A: Galunisertib": false,
        "NCT01582269:Arm B: Galunisertib + Lomustine": false,
        "NCT01582269:Arm C: Lomustine + Placebo": false
      },
      "TCGA-19-1790-01": {
        "NCT01582269:Arm A: Galunisertib": false,
        "NCT01582269:Arm B: Galunisertib + Lomustine": false,
        "NCT01582269:Arm C: Lomustine + Placebo": false
      },
      "TCGA-12-0819-01": {
        "NCT01582269:Arm A: Galunisertib": false,
        "NCT01582269:Arm B: Galunisertib + Lomustine": false,
        "NCT01582269:Arm C: Lomustine + Placebo": false
      },
      "TCGA-02-0021-01": {
        "NCT01582269:Arm A: Galunisertib": false,
        "NCT01582269:Arm B: Galunisertib + Lomustine": false,
        "NCT01582269:Arm C: Lomustine + Placebo": false
      },
      "TCGA-06-0879-01": {
        "NCT01582269:Arm A: Galunisertib": false,
        "NCT01582269:Arm B: Galunisertib + Lomustine": false,
        "NCT01582269:Arm C: Lomustine + Placebo": false
      },
      "TCGA-76-6282-01": {
        "NCT01582269:Arm A: Galunisertib": true,
        "NCT01582269:Arm B: Galunisertib + Lomustine": false,
        "NCT01582269:Arm C: Lomustine + Placebo": false
      },
      "TCGA-02-0266-01": {
        "NCT01582269:Arm A: Galunisertib": false,
        "NCT01582269:Arm B: Galunisertib + Lomustine": false,
        "NCT01582269:Arm C: Lomustine + Placebo": false
      },
      "TCGA-02-0033-01": {
        "NCT01582269:Arm A: Galunisertib": false,
        "NCT01582269:Arm B: Galunisertib + Lomustine": false,
        "NCT01582269:Arm C: Lomustine + Placebo": false
      },
      "TCGA-14-0865-01": {
        "NCT01582269:Arm A: Galunisertib": false,
        "NCT01582269:Arm B: Galunisertib + Lomustine": false,
        "NCT01582269:Arm C: Lomustine + Placebo": false
      },
      "TCGA-06-0139-01": {
        "NCT01582269:Arm A: Galunisertib": true,
        "NCT01582269:Arm B: Galunisertib + Lomustine": false,
        "NCT01582269:Arm C: Lomustine + Placebo": false
      },
      "TCGA-12-0827-01": {
        "NCT01582269:Arm A: Galunisertib": false,
        "NCT01582269:Arm B: Galunisertib + Lomustine": false,
        "NCT01582269:Arm C: Lomustine + Placebo": false
      },
      "TCGA-06-1087-01": {
        "NCT01582269:Arm A: Galunisertib": false,
        "NCT01582269:Arm B: Galunisertib + Lomustine": false,
        "NCT01582269:Arm C: Lomustine + Placebo": false
      },
      "TCGA-06-0650-01": {
        "NCT01582269:Arm A: Galunisertib": false,
        "NCT01582269:Arm B: Galunisertib + Lomustine": false,
        "NCT01582269:Arm C: Lomustine + Placebo": false
      },
      "TCGA-41-2575-01": {
        "NCT01582269:Arm A: Galunisertib": false,
        "NCT01582269:Arm B: Galunisertib + Lomustine": false,
        "NCT01582269:Arm C: Lomustine + Placebo": false
      },
      "TCGA-02-0027-01": {
        "NCT01582269:Arm A: Galunisertib": false,
        "NCT01582269:Arm B: Galunisertib + Lomustine": false,
        "NCT01582269:Arm C: Lomustine + Placebo": false
      },
      "TCGA-08-0354-01": {
        "NCT01582269:Arm A: Galunisertib": false,
        "NCT01582269:Arm B: Galunisertib + Lomustine": false,
        "NCT01582269:Arm C: Lomustine + Placebo": false
      },
      "TCGA-02-0071-01": {
        "NCT01582269:Arm A: Galunisertib": true,
        "NCT01582269:Arm B: Galunisertib + Lomustine": false,
        "NCT01582269:Arm C: Lomustine + Placebo": false
      },
      "TCGA-41-2573-01": {
        "NCT01582269:Arm A: Galunisertib": false,
        "NCT01582269:Arm B: Galunisertib + Lomustine": false,
        "NCT01582269:Arm C: Lomustine + Placebo": false
      },
      "TCGA-02-0260-01": {
        "NCT01582269:Arm A: Galunisertib": false,
        "NCT01582269:Arm B: Galunisertib + Lomustine": false,
        "NCT01582269:Arm C: Lomustine + Placebo": false
      },
      "TCGA-32-2495-01": {
        "NCT01582269:Arm A: Galunisertib": false,
        "NCT01582269:Arm B: Galunisertib + Lomustine": false,
        "NCT01582269:Arm C: Lomustine + Placebo": false
      },
      "TCGA-06-1084-01": {
        "NCT01582269:Arm A: Galunisertib": false,
        "NCT01582269:Arm B: Galunisertib + Lomustine": false,
        "NCT01582269:Arm C: Lomustine + Placebo": false
      },
      "TCGA-02-0269-01": {
        "NCT01582269:Arm A: Galunisertib": false,
        "NCT01582269:Arm B: Galunisertib + Lomustine": false,
        "NCT01582269:Arm C: Lomustine + Placebo": false
      },
      "TCGA-14-1454-01": {
        "NCT01582269:Arm A: Galunisertib": false,
        "NCT01582269:Arm B: Galunisertib + Lomustine": false,
        "NCT01582269:Arm C: Lomustine + Placebo": false
      },
      "TCGA-32-1987-01": {
        "NCT01582269:Arm A: Galunisertib": true,
        "NCT01582269:Arm B: Galunisertib + Lomustine": false,
        "NCT01582269:Arm C: Lomustine + Placebo": false
      },
      "TCGA-06-0147-01": {
        "NCT01582269:Arm A: Galunisertib": true,
        "NCT01582269:Arm B: Galunisertib + Lomustine": false,
        "NCT01582269:Arm C: Lomustine + Placebo": false
      },
      "TCGA-06-0195-01": {
        "NCT01582269:Arm A: Galunisertib": false,
        "NCT01582269:Arm B: Galunisertib + Lomustine": false,
        "NCT01582269:Arm C: Lomustine + Placebo": false
      },
      "TCGA-06-0185-01": {
        "NCT01582269:Arm A: Galunisertib": false,
        "NCT01582269:Arm B: Galunisertib + Lomustine": false,
        "NCT01582269:Arm C: Lomustine + Placebo": false
      },
      "TCGA-02-0070-01": {
        "NCT01582269:Arm A: Galunisertib": false,
        "NCT01582269:Arm B: Galunisertib + Lomustine": false,
        "NCT01582269:Arm C: Lomustine + Placebo": false
      },
      "TCGA-02-0024-01": {
        "NCT01582269:Arm A: Galunisertib": false,
        "NCT01582269:Arm B: Galunisertib + Lomustine": false,
        "NCT01582269:Arm C: Lomustine + Placebo": false
      },
      "TCGA-08-0357-01": {
        "NCT01582269:Arm A: Galunisertib": false,
        "NCT01582269:Arm B: Galunisertib + Lomustine": false,
        "NCT01582269:Arm C: Lomustine + Placebo": false
      },
      "TCGA-02-0337-01": {
        "NCT01582269:Arm A: Galunisertib": false,
        "NCT01582269:Arm B: Galunisertib + Lomustine": false,
        "NCT01582269:Arm C: Lomustine + Placebo": false
      },
      "TCGA-08-0529-01": {
        "NCT01582269:Arm A: Galunisertib": false,
        "NCT01582269:Arm B: Galunisertib + Lomustine": false,
        "NCT01582269:Arm C: Lomustine + Placebo": false
      },
      "TCGA-08-0245-01": {
        "NCT01582269:Arm A: Galunisertib": false,
        "NCT01582269:Arm B: Galunisertib + Lomustine": false,
        "NCT01582269:Arm C: Lomustine + Placebo": false
      },
      "TCGA-02-0107-01": {
        "NCT01582269:Arm A: Galunisertib": false,
        "NCT01582269:Arm B: Galunisertib + Lomustine": false,
        "NCT01582269:Arm C: Lomustine + Placebo": false
      },
      "TCGA-16-1060-01": {
        "NCT01582269:Arm A: Galunisertib": false,
        "NCT01582269:Arm B: Galunisertib + Lomustine": false,
        "NCT01582269:Arm C: Lomustine + Placebo": false
      },
      "TCGA-02-0009-01": {
        "NCT01582269:Arm A: Galunisertib": false,
        "NCT01582269:Arm B: Galunisertib + Lomustine": false,
        "NCT01582269:Arm C: Lomustine + Placebo": false
      },
      "TCGA-02-0102-01": {
        "NCT01582269:Arm A: Galunisertib": false,
        "NCT01582269:Arm B: Galunisertib + Lomustine": false,
        "NCT01582269:Arm C: Lomustine + Placebo": false
      },
      "TCGA-08-0516-01": {
        "NCT01582269:Arm A: Galunisertib": false,
        "NCT01582269:Arm B: Galunisertib + Lomustine": false,
        "NCT01582269:Arm C: Lomustine + Placebo": false
      },
      "TCGA-12-0822-01": {
        "NCT01582269:Arm A: Galunisertib": false,
        "NCT01582269:Arm B: Galunisertib + Lomustine": false,
        "NCT01582269:Arm C: Lomustine + Placebo": false
      },
      "TCGA-02-0111-01": {
        "NCT01582269:Arm A: Galunisertib": true,
        "NCT01582269:Arm B: Galunisertib + Lomustine": false,
        "NCT01582269:Arm C: Lomustine + Placebo": false
      },
      "TCGA-16-1062-01": {
        "NCT01582269:Arm A: Galunisertib": false,
        "NCT01582269:Arm B: Galunisertib + Lomustine": false,
        "NCT01582269:Arm C: Lomustine + Placebo": false
      },
      "TCGA-02-0089-01": {
        "NCT01582269:Arm A: Galunisertib": false,
        "NCT01582269:Arm B: Galunisertib + Lomustine": false,
        "NCT01582269:Arm C: Lomustine + Placebo": false
      },
      "TCGA-08-0348-01": {
        "NCT01582269:Arm A: Galunisertib": false,
        "NCT01582269:Arm B: Galunisertib + Lomustine": false,
        "NCT01582269:Arm C: Lomustine + Placebo": false
      },
      "TCGA-06-0149-01": {
        "NCT01582269:Arm A: Galunisertib": false,
        "NCT01582269:Arm B: Galunisertib + Lomustine": false,
        "NCT01582269:Arm C: Lomustine + Placebo": false
      },
      "TCGA-19-5956-01": {
        "NCT01582269:Arm A: Galunisertib": false,
        "NCT01582269:Arm B: Galunisertib + Lomustine": false,
        "NCT01582269:Arm C: Lomustine + Placebo": false
      },
      "TCGA-02-0043-01": {
        "NCT01582269:Arm A: Galunisertib": false,
        "NCT01582269:Arm B: Galunisertib + Lomustine": false,
        "NCT01582269:Arm C: Lomustine + Placebo": false
      },
      "TCGA-02-0290-01": {
        "NCT01582269:Arm A: Galunisertib": false,
        "NCT01582269:Arm B: Galunisertib + Lomustine": false,
        "NCT01582269:Arm C: Lomustine + Placebo": false
      },
      "TCGA-02-0116-01": {
        "NCT01582269:Arm A: Galunisertib": false,
        "NCT01582269:Arm B: Galunisertib + Lomustine": false,
        "NCT01582269:Arm C: Lomustine + Placebo": false
      },
      "TCGA-14-4157-01": {
        "NCT01582269:Arm A: Galunisertib": false,
        "NCT01582269:Arm B: Galunisertib + Lomustine": false,
        "NCT01582269:Arm C: Lomustine + Placebo": false
      },
      "TCGA-02-0046-01": {
        "NCT01582269:Arm A: Galunisertib": false,
        "NCT01582269:Arm B: Galunisertib + Lomustine": false,
        "NCT01582269:Arm C: Lomustine + Placebo": false
      },
      "TCGA-12-1600-01": {
        "NCT01582269:Arm A: Galunisertib": false,
        "NCT01582269:Arm B: Galunisertib + Lomustine": false,
        "NCT01582269:Arm C: Lomustine + Placebo": false
      },
      "TCGA-08-0380-01": {
        "NCT01582269:Arm A: Galunisertib": false,
        "NCT01582269:Arm B: Galunisertib + Lomustine": false,
        "NCT01582269:Arm C: Lomustine + Placebo": false
      },
      "TCGA-14-1821-01": {
        "NCT01582269:Arm A: Galunisertib": false,
        "NCT01582269:Arm B: Galunisertib + Lomustine": false,
        "NCT01582269:Arm C: Lomustine + Placebo": false
      },
      "TCGA-06-0875-01": {
        "NCT01582269:Arm A: Galunisertib": false,
        "NCT01582269:Arm B: Galunisertib + Lomustine": false,
        "NCT01582269:Arm C: Lomustine + Placebo": false
      },
      "TCGA-02-0010-01": {
        "NCT01582269:Arm A: Galunisertib": false,
        "NCT01582269:Arm B: Galunisertib + Lomustine": false,
        "NCT01582269:Arm C: Lomustine + Placebo": false
      },
      "TCGA-08-0350-01": {
        "NCT01582269:Arm A: Galunisertib": false,
        "NCT01582269:Arm B: Galunisertib + Lomustine": false,
        "NCT01582269:Arm C: Lomustine + Placebo": false
      },
      "TCGA-02-0113-01": {
        "NCT01582269:Arm A: Galunisertib": false,
        "NCT01582269:Arm B: Galunisertib + Lomustine": false,
        "NCT01582269:Arm C: Lomustine + Placebo": false
      },
      "TCGA-02-0080-01": {
        "NCT01582269:Arm A: Galunisertib": false,
        "NCT01582269:Arm B: Galunisertib + Lomustine": false,
        "NCT01582269:Arm C: Lomustine + Placebo": false
      },
      "TCGA-06-0143-01": {
        "NCT01582269:Arm A: Galunisertib": false,
        "NCT01582269:Arm B: Galunisertib + Lomustine": false,
        "NCT01582269:Arm C: Lomustine + Placebo": false
      },
      "TCGA-08-0525-01": {
        "NCT01582269:Arm A: Galunisertib": false,
        "NCT01582269:Arm B: Galunisertib + Lomustine": false,
        "NCT01582269:Arm C: Lomustine + Placebo": false
      },
      "TCGA-32-2494-01": {
        "NCT01582269:Arm A: Galunisertib": true,
        "NCT01582269:Arm B: Galunisertib + Lomustine": false,
        "NCT01582269:Arm C: Lomustine + Placebo": false
      },
      "TCGA-08-0517-01": {
        "NCT01582269:Arm A: Galunisertib": false,
        "NCT01582269:Arm B: Galunisertib + Lomustine": false,
        "NCT01582269:Arm C: Lomustine + Placebo": false
      },
      "TCGA-12-0773-01": {
        "NCT01582269:Arm A: Galunisertib": false,
        "NCT01582269:Arm B: Galunisertib + Lomustine": false,
        "NCT01582269:Arm C: Lomustine + Placebo": false
      },
      "TCGA-08-0349-01": {
        "NCT01582269:Arm A: Galunisertib": false,
        "NCT01582269:Arm B: Galunisertib + Lomustine": false,
        "NCT01582269:Arm C: Lomustine + Placebo": false
      },
      "TCGA-02-0014-01": {
        "NCT01582269:Arm A: Galunisertib": false,
        "NCT01582269:Arm B: Galunisertib + Lomustine": false,
        "NCT01582269:Arm C: Lomustine + Placebo": false
      },
      "TCGA-02-0106-01": {
        "NCT01582269:Arm A: Galunisertib": false,
        "NCT01582269:Arm B: Galunisertib + Lomustine": false,
        "NCT01582269:Arm C: Lomustine + Placebo": false
      },
      "TCGA-26-1443-01": {
        "NCT01582269:Arm A: Galunisertib": false,
        "NCT01582269:Arm B: Galunisertib + Lomustine": false,
        "NCT01582269:Arm C: Lomustine + Placebo": false
      },
      "TCGA-02-0011-01": {
        "NCT01582269:Arm A: Galunisertib": true,
        "NCT01582269:Arm B: Galunisertib + Lomustine": false,
        "NCT01582269:Arm C: Lomustine + Placebo": false
      },
      "TCGA-02-0324-01": {
        "NCT01582269:Arm A: Galunisertib": false,
        "NCT01582269:Arm B: Galunisertib + Lomustine": false,
        "NCT01582269:Arm C: Lomustine + Placebo": false
      },
      "TCGA-02-0325-01": {
        "NCT01582269:Arm A: Galunisertib": false,
        "NCT01582269:Arm B: Galunisertib + Lomustine": false,
        "NCT01582269:Arm C: Lomustine + Placebo": false
      },
      "TCGA-06-0155-01": {
        "NCT01582269:Arm A: Galunisertib": false,
        "NCT01582269:Arm B: Galunisertib + Lomustine": false,
        "NCT01582269:Arm C: Lomustine + Placebo": false
      },
      "TCGA-02-0339-01": {
        "NCT01582269:Arm A: Galunisertib": false,
        "NCT01582269:Arm B: Galunisertib + Lomustine": false,
        "NCT01582269:Arm C: Lomustine + Placebo": false
      },
      "TCGA-02-0007-01": {
        "NCT01582269:Arm A: Galunisertib": false,
        "NCT01582269:Arm B: Galunisertib + Lomustine": false,
        "NCT01582269:Arm C: Lomustine + Placebo": false
      },
      "TCGA-02-0026-01": {
        "NCT01582269:Arm A: Galunisertib": false,
        "NCT01582269:Arm B: Galunisertib + Lomustine": false,
        "NCT01582269:Arm C: Lomustine + Placebo": false
      },
      "TCGA-02-0059-01": {
        "NCT01582269:Arm A: Galunisertib": true,
        "NCT01582269:Arm B: Galunisertib + Lomustine": false,
        "NCT01582269:Arm C: Lomustine + Placebo": false
      },
      "TCGA-02-0058-01": {
        "NCT01582269:Arm A: Galunisertib": false,
        "NCT01582269:Arm B: Galunisertib + Lomustine": false,
        "NCT01582269:Arm C: Lomustine + Placebo": false
      },
      "TCGA-06-0188-01": {
        "NCT01582269:Arm A: Galunisertib": false,
        "NCT01582269:Arm B: Galunisertib + Lomustine": false,
        "NCT01582269:Arm C: Lomustine + Placebo": false
      },
      "TCGA-12-3644-01": {
        "NCT01582269:Arm A: Galunisertib": false,
        "NCT01582269:Arm B: Galunisertib + Lomustine": false,
        "NCT01582269:Arm C: Lomustine + Placebo": false
      },
      "TCGA-02-0326-01": {
        "NCT01582269:Arm A: Galunisertib": false,
        "NCT01582269:Arm B: Galunisertib + Lomustine": false,
        "NCT01582269:Arm C: Lomustine + Placebo": false
      },
      "TCGA-08-0375-01": {
        "NCT01582269:Arm A: Galunisertib": false,
        "NCT01582269:Arm B: Galunisertib + Lomustine": false,
        "NCT01582269:Arm C: Lomustine + Placebo": false
      },
      "TCGA-06-0164-01": {
        "NCT01582269:Arm A: Galunisertib": true,
        "NCT01582269:Arm B: Galunisertib + Lomustine": false,
        "NCT01582269:Arm C: Lomustine + Placebo": false
      },
      "TCGA-06-0169-01": {
        "NCT01582269:Arm A: Galunisertib": true,
        "NCT01582269:Arm B: Galunisertib + Lomustine": false,
        "NCT01582269:Arm C: Lomustine + Placebo": false
      },
      "TCGA-12-0828-01": {
        "NCT01582269:Arm A: Galunisertib": false,
        "NCT01582269:Arm B: Galunisertib + Lomustine": false,
        "NCT01582269:Arm C: Lomustine + Placebo": false
      },
      "TCGA-26-1799-01": {
        "NCT01582269:Arm A: Galunisertib": false,
        "NCT01582269:Arm B: Galunisertib + Lomustine": false,
        "NCT01582269:Arm C: Lomustine + Placebo": false
      },
      "TCGA-02-0051-01": {
        "NCT01582269:Arm A: Galunisertib": false,
        "NCT01582269:Arm B: Galunisertib + Lomustine": false,
        "NCT01582269:Arm C: Lomustine + Placebo": false
      },
      "TCGA-06-0127-01": {
        "NCT01582269:Arm A: Galunisertib": false,
        "NCT01582269:Arm B: Galunisertib + Lomustine": false,
        "NCT01582269:Arm C: Lomustine + Placebo": false
      },
      "TCGA-12-0820-01": {
        "NCT01582269:Arm A: Galunisertib": false,
        "NCT01582269:Arm B: Galunisertib + Lomustine": false,
        "NCT01582269:Arm C: Lomustine + Placebo": false
      },
      "TCGA-06-0876-01": {
        "NCT01582269:Arm A: Galunisertib": false,
        "NCT01582269:Arm B: Galunisertib + Lomustine": false,
        "NCT01582269:Arm C: Lomustine + Placebo": false
      },
      "TCGA-06-0208-01": {
        "NCT01582269:Arm A: Galunisertib": false,
        "NCT01582269:Arm B: Galunisertib + Lomustine": false,
        "NCT01582269:Arm C: Lomustine + Placebo": false
      },
      "TCGA-02-0432-01": {
        "NCT01582269:Arm A: Galunisertib": false,
        "NCT01582269:Arm B: Galunisertib + Lomustine": false,
        "NCT01582269:Arm C: Lomustine + Placebo": false
      },
      "TCGA-08-0520-01": {
        "NCT01582269:Arm A: Galunisertib": false,
        "NCT01582269:Arm B: Galunisertib + Lomustine": false,
        "NCT01582269:Arm C: Lomustine + Placebo": false
      },
      "TCGA-08-0521-01": {
        "NCT01582269:Arm A: Galunisertib": false,
        "NCT01582269:Arm B: Galunisertib + Lomustine": false,
        "NCT01582269:Arm C: Lomustine + Placebo": false
      }
    }
  }
}